keyflare/__init__.py
keyflare/__main__.py
keyflare/gui.py
keyflare/image_pipeline.py
keyflare/system.py
keyflare/usages.py
keyflare-1.2.0.dist-info/LICENSE.txt
keyflare-1.2.0.dist-info/METADATA
keyflare-1.2.0.dist-info/WHEEL
keyflare-1.2.0.dist-info/entry_points.txt
keyflare-1.2.0.dist-info/top_level.txt
keyflare-1.2.0.dist-info/RECORD
