Metadata-Version: 2.1
Name: keyflare
Version: 1.2.0
Summary: Control your mouse with your keyboard through KeyFlare
Home-page: https://github.com/Pshah2023/keyflare
Author: Pranit Shah
Author-email: ppshah2023@gmail.com
License: MIT
Classifier: Development Status :: 5 - Production/Stable
Classifier: Intended Audience :: Developers
Classifier: License :: OSI Approved :: MIT License
Classifier: Programming Language :: Python :: 3
Classifier: Topic :: Software Development :: Libraries :: Python Modules
Classifier: Topic :: Utilities
License-File: LICENSE.txt
Requires-Dist: numpy >=1.23
Requires-Dist: opencv-python ==4.7.0.72
Requires-Dist: Pillow ==9.5.0
Requires-Dist: PyAutoGUI ==0.9.54
Requires-Dist: pynput ==1.7.6
Requires-Dist: pyperclip ==1.8.2
Requires-Dist: pyscreenshot ==3.1
Requires-Dist: Rtree ==1.0.1
Requires-Dist: numpy ==1.24.3
Provides-Extra: dev
Requires-Dist: pytesseract ==0.3.1 ; extra == 'dev'
Requires-Dist: twine ==4.0.2 ; extra == 'dev'
Requires-Dist: wheel ==0.41.3 ; extra == 'dev'
Requires-Dist: pytest ==7.4.2 ; extra == 'dev'
Requires-Dist: pytest-benchmark ==4.0.0 ; extra == 'dev'
Requires-Dist: setuptools ==68.2.2 ; extra == 'dev'
Requires-Dist: black ==23.11.0 ; extra == 'dev'
Requires-Dist: pylint ==3.0.2 ; extra == 'dev'
